infoapps_mlops_sdk/__init__.py
infoapps_mlops_sdk/core.py
infoapps_mlops_sdk/general_utilities.py
infoapps_mlops_sdk/test_core.py
infoapps_mlops_sdk/types.py
infoapps_mlops_sdk/integrations/__init__.py
infoapps_mlops_sdk/integrations/keras_callback.py
infoapps_mlops_sdk/integrations/pytorch_callback.py
infoapps_mlops_sdk/integrations/pytorchlightening_callback.py
infoapps_mlops_sdk/sdk_logging/__init__.py
infoapps_mlops_sdk/sdk_logging/http_handler.py
infoapps_mlops_sdk/tracking/__init__.py
infoapps_mlops_sdk/tracking/experiment.py
infoapps_mlops_sdk/tracking/platform.py
infoapps_mlops_sdk-0.0.33.dist-info/LICENSE
infoapps_mlops_sdk-0.0.33.dist-info/METADATA
infoapps_mlops_sdk-0.0.33.dist-info/WHEEL
infoapps_mlops_sdk-0.0.33.dist-info/top_level.txt
infoapps_mlops_sdk-0.0.33.dist-info/RECORD
