Metadata-Version: 2.1
Name: infoapps-mlops-sdk
Version: 0.0.33
Summary: A custom MLOps SDK
Home-page: https://prodgit.apple.com/feldspar/mlops-py
Author: Renaldo Williams
Author-email: renaldo_williams@apple.com
License: UNKNOWN
Platform: UNKNOWN
Classifier: Programming Language :: Python :: 3
Classifier: License :: OSI Approved :: MIT License
Classifier: Operating System :: OS Independent
Requires-Python: >=3.8
License-File: LICENSE
Requires-Dist: turihub ==2.18.0
Requires-Dist: pytorch-lightning ==2.1.1
Requires-Dist: torch ==2.4.1
Requires-Dist: keras ==2.15.0
Requires-Dist: tensorflow ==2.15.0
